infoselect/__init__.py
infoselect/gmm.py
infoselect/mi.py
infoselect-1.0.3.dist-info/LICENSE.txt
infoselect-1.0.3.dist-info/METADATA
infoselect-1.0.3.dist-info/WHEEL
infoselect-1.0.3.dist-info/top_level.txt
infoselect-1.0.3.dist-info/RECORD
