Metadata-Version: 2.1
Name: infoselect
Version: 1.0.3
Summary: Mutual Information Based Feature Selection in Python.
Home-page: https://github.com/felipemaiapolo/infoselect
Author: Felipe Maia Polo & Felipe Leno da Silva
Author-email: felipemaiapolo@gmail.com, f.leno@usp.br
Classifier: Programming Language :: Python :: 3
Classifier: License :: OSI Approved :: MIT License
Classifier: Operating System :: OS Independent
License-File: LICENSE.txt
Requires-Dist: scipy
Requires-Dist: numpy
Requires-Dist: pandas
Requires-Dist: sklearn
Requires-Dist: matplotlib
